pycis/cli/__init__.py
pycis/cli/cmdtree/__init__.py
pycis/cli/cmdtree/datastore/__init__.py
pycis/cli/cmdtree/datastore/constants.py
pycis/cli/cmdtree/datastore/couchdb/__init__.py
pycis/cli/cmdtree/datastore/couchdb/initialize.py
pycis/cli/cmdtree/datastore/couchdb/publish.py
pycis/cli/cmdtree/datastore/mongodb/__init__.py
pycis/cli/cmdtree/datastore/mongodb/publish.py
pycis/cli/cmdtree/document/__init__.py
pycis/cli/cmdtree/document/build/__init__.py
pycis/cli/cmdtree/document/build/addbyproduct.py
pycis/cli/cmdtree/document/build/addchange.py
pycis/cli/cmdtree/document/build/initialize.py
pycis/cli/cmdtree/document/build/setjobdetail.py
pycis/cli/cmdtree/document/build/update.py
pycis/cli/cmdtree/document/configuration/__init__.py
pycis/cli/cmdtree/document/configuration/decrypt.py
pycis/cli/cmdtree/document/configuration/encrypt.py
pycis/cli/cmdtree/document/testrun/__init__.py
pycis/cli/cmdtree/document/testrun/create.py
pycis/cli/cmdtree/tracking/__init__.py
pycis/cli/cmdtree/tracking/jira/__init__.py
pycis/cli/cmdtree/tracking/jira/comment.py
pycis/cli/pycis_command.py
pycis_cli-0.1.5.dist-info/WHEEL
pycis_cli-0.1.5.dist-info/entry_points.txt
pycis_cli-0.1.5.dist-info/LICENSE.txt
pycis_cli-0.1.5.dist-info/METADATA
pycis_cli-0.1.5.dist-info/RECORD
