Metadata-Version: 2.1
Name: pycis-cli
Version: 0.1.5
Summary: Python Continuous Integration System (PyCIS) - CLI Tools
License: LICENSE.txt
Keywords: python
Requires-Python: >=3.9,<4.0
Classifier: License :: OSI Approved :: MIT License
Classifier: License :: Other/Proprietary License
Classifier: Operating System :: POSIX
Classifier: Programming Language :: Python :: 3
Classifier: Programming Language :: Python :: 3.9
Classifier: Programming Language :: Python :: 3.10
Classifier: Programming Language :: Python :: 3.11
Classifier: Programming Language :: Python :: 3
Provides-Extra: couchdb
Provides-Extra: jira
Provides-Extra: mongodb
Requires-Dist: click (>=8.1.4,<9.0.0)
Requires-Dist: couchdb (>=1.2,<2.0) ; extra == "couchdb"
Requires-Dist: jira (>=3.8.0,<4.0.0) ; extra == "jira"
Requires-Dist: mojo-config (>=1.3.20,<1.4.0)
Requires-Dist: mojo-credentials (>=1.3.10,<1.4.0)
Requires-Dist: mojo-xmodules (>=1.3.0,<1.4.0)
Requires-Dist: pymongo (>=4.0.0,<5.0.0) ; extra == "mongodb"
